{
  "hash": "5d2cb95b",
  "configHash": "9c5a476e",
  "lockfileHash": "6ba58a18",
  "browserHash": "c4f393e4",
  "optimized": {
    "react": {
      "src": "../../node_modules/react/index.js",
      "file": "react.js",
      "fileHash": "a0ce7acc",
      "needsInterop": true
    },
    "react-dom/client": {
      "src": "../../node_modules/react-dom/client.js",
      "file": "react-dom_client.js",
      "fileHash": "4b27416d",
      "needsInterop": true
    }
  },
  "chunks": {
    "chunk-B2WE2YPZ": {
      "file": "chunk-B2WE2YPZ.js"
    }
  }
}